fakestack/__init__.py
fakestack/runner.py
fakestack/bin/fakestack-darwin-amd64
fakestack/bin/fakestack-darwin-arm64
fakestack/bin/fakestack-linux-amd64
fakestack/bin/fakestack-linux-arm64
fakestack/bin/fakestack-windows-amd64.exe
fakestack-1.1.0.dist-info/METADATA
fakestack-1.1.0.dist-info/WHEEL
fakestack-1.1.0.dist-info/entry_points.txt
fakestack-1.1.0.dist-info/top_level.txt
fakestack-1.1.0.dist-info/RECORD
