Metadata-Version: 2.4
Name: fakestack
Version: 1.1.0
Summary: Full-stack fake data generator - Generate databases and APIs from JSON schemas
Author-email: Devendra Pratap <dps.manit@gmail.com>
Maintainer-email: Devendra Pratap <dps.manit@gmail.com>
License: MIT
Project-URL: Homepage, https://github.com/0xdps/fake-stack
Project-URL: Documentation, https://fake-stack.readthedocs.io/
Project-URL: Repository, https://github.com/0xdps/fake-stack.git
Project-URL: Issues, https://github.com/0xdps/fake-stack/issues
Project-URL: Changelog, https://github.com/0xdps/fake-stack/blob/trunk/CHANGELOG.md
Keywords: faker,dummy,db,database,schema,generate,generator,fakestack,test-data,fake-data,mock,backend,api
Classifier: Development Status :: 4 - Beta
Classifier: Intended Audience :: Developers
Classifier: License :: OSI Approved :: MIT License
Classifier: Operating System :: OS Independent
Classifier: Programming Language :: Python :: 3
Classifier: Programming Language :: Python :: 3.8
Classifier: Programming Language :: Python :: 3.9
Classifier: Programming Language :: Python :: 3.10
Classifier: Programming Language :: Python :: 3.11
Classifier: Programming Language :: Python :: 3.12
Classifier: Programming Language :: Python :: 3.13
Classifier: Topic :: Software Development :: Libraries :: Python Modules
Classifier: Topic :: Software Development :: Testing
Classifier: Topic :: Database
Requires-Python: >=3.8
Provides-Extra: minimal
Provides-Extra: dev
Requires-Dist: pytest>=7.0.0; extra == "dev"
Requires-Dist: pytest-cov>=4.0.0; extra == "dev"
Requires-Dist: black>=23.0.0; extra == "dev"
Requires-Dist: isort>=5.12.0; extra == "dev"
Requires-Dist: flake8>=6.0.0; extra == "dev"
Requires-Dist: mypy>=1.0.0; extra == "dev"
Requires-Dist: build>=0.10.0; extra == "dev"
Requires-Dist: twine>=4.0.0; extra == "dev"
Provides-Extra: docs
Requires-Dist: sphinx>=5.0.0; extra == "docs"
Requires-Dist: sphinx-rtd-theme>=1.0.0; extra == "docs"
Requires-Dist: myst-parser>=0.18.0; extra == "docs"
